LICENSE.txt
MANIFEST.in
README.md
setup.py
django_simplecrop.egg-info/PKG-INFO
django_simplecrop.egg-info/SOURCES.txt
django_simplecrop.egg-info/dependency_links.txt
django_simplecrop.egg-info/not-zip-safe
django_simplecrop.egg-info/requires.txt
django_simplecrop.egg-info/top_level.txt
simplecrop/__init__.py
simplecrop/template_tags.py
simplecrop/urls.py
simplecrop/utils.py
simplecrop/views.py
simplecrop/static/simplecrop/css/bootstrap-responsive.min.css
simplecrop/static/simplecrop/css/bootstrap.min.css
simplecrop/static/simplecrop/css/jquery.Jcrop.css
simplecrop/static/simplecrop/css/utils_upload.css
simplecrop/static/simplecrop/img/loader.gif
simplecrop/static/simplecrop/js/jquery-1.9.1.min.js
simplecrop/static/simplecrop/js/jquery-form.js
simplecrop/static/simplecrop/js/jquery.Jcrop.js
simplecrop/templates/simpleCrop/crop.html