Metadata-Version: 1.1
Name: django-simplecrop
Version: 1.0.4
Summary: A simple module to make easier crop images in Django admin.
Home-page: https://github.com/feliperrego/django-simplecrop
Author: Felipe R. Rêgo
Author-email: feliperrego@gmail.com
License: BSD
Keywords: crop,django
Platform: UNKNOWN
Classifier: Programming Language :: Python
Classifier: Topic :: Software Development :: Libraries :: Python Modules
Classifier: Framework :: Django
Classifier: Environment :: Web Environment
